setup.py
distributions_rawatsd/Binomialdistribution.py
distributions_rawatsd/Gaussiandistribution.py
distributions_rawatsd/Generaldistribution.py
distributions_rawatsd/__init__.py
distributions_rawatsd.egg-info/PKG-INFO
distributions_rawatsd.egg-info/SOURCES.txt
distributions_rawatsd.egg-info/dependency_links.txt
distributions_rawatsd.egg-info/not-zip-safe
distributions_rawatsd.egg-info/top_level.txt