Metadata-Version: 2.1
Name: distributions-rawatsd
Version: 0.2
Summary: Gaussian distributions
Home-page: UNKNOWN
License: UNKNOWN
Platform: UNKNOWN
